IAIP/Sequential_Circuit_Design/d_flip_flop/d_ff.v
module d_ff(
    input D,
    input clk,
    output reg Q
);

always @(posedge clk)
begin
    Q <= D;
end

endmodule

IAIP/Sequential_Circuit_Design/d_flip_flop/d_ff_tb.v
`timescale 1ns/1ps

module d_ff_tb;

reg D,clk;
wire Q;

d_ff uut(
.D(D),
.clk(clk),
.Q(Q)
);

always #5 clk=~clk;

initial begin

$dumpfile("d_ff.vcd");
$dumpvars(0,d_ff_tb);

clk=0;

D=0;#10;
D=1;#10;
D=0;#10;
D=1;#10;

$finish;

end

endmodule

IAIP/Sequential_Circuit_Design/d_flip_flop/d_ff.vcd
$date
	Mon Jun 01 14:07:00 2026
$end
$version
	Icarus Verilog
$end
$timescale
	1ps
$end
$scope module d_ff_tb $end
$var wire 1 ! Q $end
$var reg 1 " D $end
$var reg 1 # clk $end
$scope module uut $end
$var wire 1 " D $end
$var wire 1 # clk $end
$var reg 1 ! Q $end
$upscope $end
$upscope $end
$enddefinitions $end
$comment Show the parameter values. $end
$dumpall
$end
#0
$dumpvars
0#
0"
x!
$end
#5000
0!
1#
#10000
0#
1"
#15000
1!
1#
#20000
0#
0"
#25000
0!
1#
#30000
0#
1"
#35000
1!
1#
