IAIP/Sequential_Circuit_Design/counter/counter.v
module counter(
    input clk,
    output reg [3:0] count = 0
);

always @(posedge clk)
begin
    count <= count + 1;
end

endmodule

IAIP/Sequential_Circuit_Design/counter/counter_tb.v
`timescale 1ns/1ps

module counter_tb;

reg clk;
wire [3:0] count;

counter uut(
.clk(clk),
.count(count)
);

always #5 clk=~clk;

initial begin

$dumpfile("counter.vcd");
$dumpvars(0,counter_tb);

clk=0;

#100;

$finish;

end

endmodule

IAIP/Sequential_Circuit_Design/counter/counter.vcd
$date
	Mon Jun 01 14:19:45 2026
$end
$version
	Icarus Verilog
$end
$timescale
	1ps
$end
$scope module counter_tb $end
$var wire 4 ! count [3:0] $end
$var reg 1 " clk $end
$scope module uut $end
$var wire 1 " clk $end
$var reg 4 # count [3:0] $end
$upscope $end
$upscope $end
$enddefinitions $end
$comment Show the parameter values. $end
$dumpall
$end
#0
$dumpvars
b0 #
0"
b0 !
$end
#5000
b1 !
b1 #
1"
#10000
0"
#15000
b10 !
b10 #
1"
#20000
0"
#25000
b11 !
b11 #
1"
#30000
0"
#35000
b100 !
b100 #
1"
#40000
0"
#45000
b101 !
b101 #
1"
#50000
0"
#55000
b110 !
b110 #
1"
#60000
0"
#65000
b111 !
b111 #
1"
#70000
0"
#75000
b1000 !
b1000 #
1"
#80000
0"
#85000
b1001 !
b1001 #
1"
#90000
0"
#95000
b1010 !
b1010 #
1"
