IAIP/Sequential_Circuit_Design/shift_register/shift_register.v
module shift_register(
    input clk,
    input serial_in,
    output reg [3:0] Q
);

initial begin
    Q = 4'b0000;
end

always @(posedge clk)
begin
    Q <= {Q[2:0], serial_in};
end

endmodule

IAIP/Sequential_Circuit_Design/shift_register/shift_register_tb.v
`timescale 1ns/1ps

module shift_register_tb;

reg clk;
reg serial_in;

wire [3:0] Q;

shift_register uut(
    .clk(clk),
    .serial_in(serial_in),
    .Q(Q)
);

always #5 clk = ~clk;

initial begin

    $dumpfile("shift_register.vcd");
    $dumpvars(0, shift_register_tb);

    clk = 0;

    serial_in = 1; #10;
    serial_in = 0; #10;
    serial_in = 1; #10;
    serial_in = 1; #10;
    serial_in = 0; #10;
    serial_in = 1; #10;

    $finish;

end

endmodule

IAIP/Sequential_Circuit_Design/shift_register/shift_register.vcd
$date
	Tue Jun 02 16:13:20 2026
$end
$version
	Icarus Verilog
$end
$timescale
	1ps
$end
$scope module shift_register_tb $end
$var wire 4 ! Q [3:0] $end
$var reg 1 " clk $end
$var reg 1 # serial_in $end
$scope module uut $end
$var wire 1 " clk $end
$var wire 1 # serial_in $end
$var reg 4 $ Q [3:0] $end
$upscope $end
$upscope $end
$enddefinitions $end
$comment Show the parameter values. $end
$dumpall
$end
#0
$dumpvars
b0 $
1#
0"
b0 !
$end
#5000
b1 !
b1 $
1"
#10000
0"
0#
#15000
b10 !
b10 $
1"
#20000
0"
1#
#25000
b101 !
b101 $
1"
#30000
0"
#35000
b1011 !
b1011 $
1"
#40000
0"
0#
#45000
b110 !
b110 $
1"
#50000
0"
1#
#55000
b1101 !
b1101 $
1"
