IAIP/Sequential_Circuit_Design/jk_flip_flop/jk_ff.v
module jk_ff(
    input J,
    input K,
    input clk,
    output reg Q
);

always @(posedge clk)
begin
    case({J,K})
        2'b00: Q <= Q;
        2'b01: Q <= 0;
        2'b10: Q <= 1;
        2'b11: Q <= ~Q;
    endcase
end

endmodule

IAIP/Sequential_Circuit_Design/jk_flip_flop/jk_ff_tb.v
`timescale 1ns/1ps

module jk_ff_tb;

reg J,K,clk;
wire Q;

jk_ff uut(
.J(J),
.K(K),
.clk(clk),
.Q(Q)
);

always #5 clk=~clk;

initial begin

$dumpfile("jk_ff.vcd");
$dumpvars(0,jk_ff_tb);

clk=0;

J=0;K=0;#10;
J=1;K=0;#10;
J=0;K=1;#10;
J=1;K=1;#20;

$finish;

end

endmodule

IAIP/Sequential_Circuit_Design/jk_flip_flop/jk_ff.vcd
$date
	Mon Jun 01 14:06:38 2026
$end
$version
	Icarus Verilog
$end
$timescale
	1ps
$end
$scope module jk_ff_tb $end
$var wire 1 ! Q $end
$var reg 1 " J $end
$var reg 1 # K $end
$var reg 1 $ clk $end
$scope module uut $end
$var wire 1 " J $end
$var wire 1 # K $end
$var wire 1 $ clk $end
$var reg 1 ! Q $end
$upscope $end
$upscope $end
$enddefinitions $end
$comment Show the parameter values. $end
$dumpall
$end
#0
$dumpvars
0$
0#
0"
x!
$end
#5000
1$
#10000
0$
1"
#15000
1!
1$
#20000
0$
1#
0"
#25000
0!
1$
#30000
0$
1"
#35000
1!
1$
#40000
0$
#45000
0!
1$
