IAIP/Sequential_Circuit_Design/traffic_fsm/traffic_fsm.v
module traffic_fsm(
    input clk,
    output reg [1:0] state
);

parameter RED=2'b00;
parameter YELLOW=2'b01;
parameter GREEN=2'b10;

always @(posedge clk)
begin

case(state)

RED:
state <= GREEN;

GREEN:
state <= YELLOW;

YELLOW:
state <= RED;

default:
state <= RED;

endcase

end

endmodule

IAIP/Sequential_Circuit_Design/traffic_fsm/traffic_fsm_tb.v
`timescale 1ns/1ps

module traffic_fsm_tb;

reg clk;

wire [1:0] state;

traffic_fsm uut(
.clk(clk),
.state(state)
);

always #5 clk=~clk;

initial begin

$dumpfile("traffic_fsm.vcd");
$dumpvars(0,traffic_fsm_tb);

clk=0;

#100;

$finish;

end

endmodule

IAIP/Sequential_Circuit_Design/traffic_fsm/traffic_fsm.vcd
$date
	Mon Jun 01 14:10:53 2026
$end
$version
	Icarus Verilog
$end
$timescale
	1ps
$end
$scope module traffic_fsm_tb $end
$var wire 2 ! state [1:0] $end
$var reg 1 " clk $end
$scope module uut $end
$var wire 1 " clk $end
$var parameter 2 # GREEN $end
$var parameter 2 $ RED $end
$var parameter 2 % YELLOW $end
$var reg 2 & state [1:0] $end
$upscope $end
$upscope $end
$enddefinitions $end
$comment Show the parameter values. $end
$dumpall
b1 %
b0 $
b10 #
$end
#0
$dumpvars
bx &
0"
bx !
$end
#5000
b0 !
b0 &
1"
#10000
0"
#15000
b10 !
b10 &
1"
#20000
0"
#25000
b1 !
b1 &
1"
#30000
0"
#35000
b0 !
b0 &
1"
#40000
0"
#45000
b10 !
b10 &
1"
#50000
0"
#55000
b1 !
b1 &
1"
#60000
0"
#65000
b0 !
b0 &
1"
#70000
0"
#75000
b10 !
b10 &
1"
#80000
0"
#85000
b1 !
b1 &
1"
#90000
0"
#95000
b0 !
b0 &
1"
